facsimile/__init__.py
facsimile/eval.py
facsimile/model.py
facsimile/plotting.py
facsimile/utils.py
facsimile_py-0.1.0.dist-info/METADATA
facsimile_py-0.1.0.dist-info/WHEEL
facsimile_py-0.1.0.dist-info/licenses/LICENSE
facsimile_py-0.1.0.dist-info/RECORD
