Metadata-Version: 2.3
Name: FACSIMILE-py
Version: 0.1.0
Summary: A package for predicting questionnaire scores from reduced item sets
Project-URL: Homepage, https://facsimile.thewiselab.org/
Project-URL: Repository, https://github.com/the-wise-lab/FACSIMILE
Author-email: Toby Wise <toby.wise@kcl.ac.uk>
License: MIT
License-File: LICENSE
Requires-Dist: joblib
Requires-Dist: matplotlib
Requires-Dist: pandas
Requires-Dist: requests
Requires-Dist: scikit-learn
Requires-Dist: tqdm
